{
  "branch": null,
  "claimed_by": null,
  "closed_at": null,
  "closed_children": [],
  "created_at": "2026-05-20T01:32:17.250460941Z",
  "delivered_in": null,
  "depends_on": [],
  "description": "\n\n\n## 🤖 New release\n\n* `balls`: 0.3.6 -> 0.3.7\n\n<details><summary><i><b>Changelog</b></i></summary><p>\n\n<blockquote>\n\n## [0.3.7](https://github.com/mudbungie/balls/compare/v0.3.6...v0.3.7) - 2026-04-22\n\n### Changes\n\n- brighten P2 priority dot [bl-e6bb]\n- name the remove-task path, narrow 'deferred' [bl-ad36]\n- add --limit N to cap the queue [bl-2b5a]\n- reflect CLI overhaul in README and SKILL.md [bl-1eb8]\n- epic bars in list/show and progress object in --json [bl-8dcf]\n- header + relations + wrapped notes layout [bl-adaf]\n- status column + parent hint line [bl-21a5]\n- status-grouped, parent-nested layout [bl-25db]\n- dep tree: parent/child rendering with box-drawing [bl-577d]\n</blockquote>\n\n\n</p></details>\n\n---\nThis PR was generated with [release-plz](https://github.com/release-plz/release-plz/).",
  "external": {"github-issues":{"github_issues":{"issue":{"last_synced_status":"open","number":10,"source":"github","state":"closed","synced_at":"2026-05-20T01:32:17.137083686+00:00","url":"https://github.com/mudbungie/balls/pull/10"}}}},
  "id": "bl-1436",
  "links": [],
  "parent": null,
  "priority": 3,
  "status": "open",
  "synced_at": {"github-issues":"2026-05-20T01:32:17.250463265Z"},
  "tags": [],
  "title": "chore: release v0.3.7",
  "type": "task",
  "updated_at": "2026-05-20T01:32:17.250460941Z"
}
