{
  "branch": "work/bl-650b",
  "claimed_by": "mark",
  "closed_at": null,
  "closed_children": [],
  "created_at": "2026-05-20T00:48:12.257464527Z",
  "delivered_in": "a07176f8814382f7d47e0276968b54c26b1fcfe5",
  "depends_on": [],
  "description": "rust 1.95.0 enabled clippy::map_unwrap_or as an error-by-default lint (denied via RUSTFLAGS=-D warnings in CI). Local rust 1.94 doesn't trigger it; CI does. Replace .map(...).unwrap_or(false) with .is_ok_and(...). Blocks the v0.4.0 release CI.",
  "external": {"github-issues":{"issue":{"last_synced_status":"review","number":19,"source":"balls","state":"open","synced_at":"2026-05-20T00:49:12.919733473+00:00","url":"https://github.com/mudbungie/balls/issues/19"}}},
  "id": "bl-650b",
  "links": [],
  "parent": null,
  "priority": 1,
  "repo": "git@github.com:mudbungie/balls.git",
  "status": "review",
  "synced_at": {"github-issues":"2026-05-20T00:49:12.947593611Z"},
  "tags": ["fix","clippy"],
  "title": "Fix map_unwrap_or clippy lint on doctor.rs (rust 1.95)",
  "type": "task",
  "updated_at": "2026-05-20T00:49:12.947599712Z"
}
