{
  "branch": null,
  "claimed_by": null,
  "closed_at": null,
  "closed_children": [],
  "created_at": "2026-06-05T08:28:18.895368540Z",
  "delivered_in": null,
  "depends_on": ["bl-5d56","bl-dfbd"],
  "description": "Sibling binary owning the CODE worktree (git worktree of project repo on work/<id>). Kind-blind, stateless-across-ops (derived path = f(binding,id)). Hooks: claim.post materialize, close.pre deliver (squash→integration, sorts last), close.post teardown (+cwd guard), unclaim/drop.post release. delivered_in = git-log-grep query. §14 rollback tiers.",
  "external": {},
  "id": "bl-f813",
  "links": [],
  "parent": "bl-72a8",
  "priority": 3,
  "repo": "git@github.com:mudbungie/balls.git",
  "status": "open",
  "tags": [],
  "title": "§11 delivery/worktree plugin (direct variant)",
  "type": "task",
  "updated_at": "2026-06-05T08:28:18.895368540Z"
}
